hail/__init__.py
hail/builtin_references.py
hail/conftest.py
hail/context.py
hail/hail_logging.py
hail/matrixtable.py
hail/table.py
hail/version.py
hail/backend/__init__.py
hail/backend/backend.py
hail/backend/hail-all-spark.jar
hail/backend/local_backend.py
hail/backend/py4j_backend.py
hail/backend/service_backend.py
hail/backend/spark_backend.py
hail/experimental/__init__.py
hail/experimental/datasets.json
hail/experimental/datasets.py
hail/experimental/datasets_metadata.py
hail/experimental/db.py
hail/experimental/export_entries_by_col.py
hail/experimental/expressions.py
hail/experimental/filtering_allele_frequency.py
hail/experimental/full_outer_join_mt.py
hail/experimental/function.py
hail/experimental/haplotype_freq_em.py
hail/experimental/import_gtf.py
hail/experimental/interact.py
hail/experimental/ld_score_regression.py
hail/experimental/ldscore.py
hail/experimental/ldscsim.py
hail/experimental/lens.py
hail/experimental/loop.py
hail/experimental/pca.py
hail/experimental/phase_by_transmission.py
hail/experimental/plots.py
hail/experimental/table_ndarray_utils.py
hail/experimental/tidyr.py
hail/experimental/time.py
hail/experimental/write_multiple.py
hail/experimental/sparse_mt/__init__.py
hail/experimental/sparse_mt/densify.py
hail/experimental/sparse_mt/sparse_split_multi.py
hail/expr/__init__.py
hail/expr/blockmatrix_type.py
hail/expr/builders.py
hail/expr/functions.py
hail/expr/matrix_type.py
hail/expr/nat.py
hail/expr/table_type.py
hail/expr/type_parsing.py
hail/expr/types.py
hail/expr/aggregators/__init__.py
hail/expr/aggregators/aggregators.py
hail/expr/expressions/__init__.py
hail/expr/expressions/base_expression.py
hail/expr/expressions/expression_typecheck.py
hail/expr/expressions/expression_utils.py
hail/expr/expressions/indices.py
hail/expr/expressions/typed_expressions.py
hail/fs/__init__.py
hail/fs/hadoop_fs.py
hail/genetics/__init__.py
hail/genetics/allele_type.py
hail/genetics/call.py
hail/genetics/locus.py
hail/genetics/pedigree.py
hail-0.2.136.dist-info/METADATA
hail-0.2.136.dist-info/WHEEL
hail-0.2.136.dist-info/entry_points.txt
hail-0.2.136.dist-info/top_level.txt
hail-0.2.136.dist-info/RECORD
