Metadata-Version: 2.4
Name: hail
Version: 0.2.136
Summary: Scalable library for exploring and analyzing genomic data.
Home-page: https://hail.is
Author: Hail Team
Author-email: hail@broadinstitute.org
Project-URL: Documentation, https://hail.is/docs/0.2/
Project-URL: Repository, https://github.com/hail-is/hail
Project-URL: Change Log, https://hail.is/docs/0.2/change_log.html
Classifier: Programming Language :: Python :: 3
Classifier: License :: OSI Approved :: MIT License
Requires-Python: >=3.10
Requires-Dist: aiodns<3,>=2.0.0
Requires-Dist: aiohttp<4,>=3.11.16
Requires-Dist: azure-identity<2,>=1.23.0
Requires-Dist: azure-mgmt-storage==20.1.0
Requires-Dist: azure-storage-blob<13,>=12.11.0
Requires-Dist: boto3<2.0,>=1.17
Requires-Dist: botocore<2.0,>=1.20
Requires-Dist: dill<0.5,>=0.4.0
Requires-Dist: frozenlist<2,>=1.3.1
Requires-Dist: google-auth<3,>=2.14.1
Requires-Dist: google-auth-oauthlib<1,>=0.5.2
Requires-Dist: humanize<5,>=4.0
Requires-Dist: janus<1.1,>=0.6
Requires-Dist: nest_asyncio<2,>=1.5.8
Requires-Dist: orjson<4,>=3.9.15
Requires-Dist: rich<13,>=12.6.0
Requires-Dist: typer<1,>=0.9.0
Requires-Dist: python-json-logger<3,>=2.0.2
Requires-Dist: pyyaml<7.0,>=6.0
Requires-Dist: sortedcontainers<3,>=2.4.0
Requires-Dist: tabulate<1,>=0.8.9
Requires-Dist: uvloop<1,>=0.19.0; sys_platform != "win32"
Requires-Dist: jproperties<3,>=2.1.1
Requires-Dist: avro<1.12,>=1.10
Requires-Dist: bokeh<3.5,>=3
Requires-Dist: decorator<5
Requires-Dist: Deprecated<1.3,>=1.2.10
Requires-Dist: numpy<3,>=2
Requires-Dist: pandas<3,>=2
Requires-Dist: parsimonious<1
Requires-Dist: plotly<6,>=5.18.0
Requires-Dist: pyspark<3.6,>=3.5.0
Requires-Dist: requests<3,>=2.32.4
Requires-Dist: scipy<2,>1.13
Dynamic: author
Dynamic: author-email
Dynamic: classifier
Dynamic: description
Dynamic: description-content-type
Dynamic: home-page
Dynamic: project-url
Dynamic: requires-dist
Dynamic: requires-python
Dynamic: summary
